{
  "plugins": [
    {
      "repo": "regional-planning",
      "name": "regional-planning"
    },
    {
      "repo": "HydroFlow",
      "name": "HydroFlow",
      "org": "FreshwaterNetwork"
    },	
    {   
      "repo": "OysterFlow",
      "name": "OysterFlow",
      "org": "FreshwaterNetwork"
    },
    {
      "repo": "water-quality",
      "name": "water-quality",
      "org": "FreshwaterNetwork"
    },
    {
      "repo": "conservation-delivery-application",
      "name": "conservation-delivery-application",
      "org": "FreshwaterNetwork"
    },
    {
      "repo": "regional-planning",
      "name": "hydrologic-alterations"
    }
  ]
}
